video2ppt/__init__.py
video2ppt/compare.py
video2ppt/images2pdf.py
video2ppt/video2ppt.py
extract_video_ppt-1.1.2.dist-info/LICENSE
extract_video_ppt-1.1.2.dist-info/METADATA
extract_video_ppt-1.1.2.dist-info/WHEEL
extract_video_ppt-1.1.2.dist-info/entry_points.txt
extract_video_ppt-1.1.2.dist-info/top_level.txt
extract_video_ppt-1.1.2.dist-info/RECORD
