Metadata-Version: 2.1
Name: extract-video-ppt
Version: 1.1.2
Summary: support export ppt from a video
Author: wudu
Author-email: 296525335@qq.com
License: UNKNOWN
Platform: UNKNOWN
Classifier: Programming Language :: Python :: 3
Classifier: License :: OSI Approved :: MIT License
Classifier: Operating System :: OS Independent
License-File: LICENSE
